dbobjectcreator/DbObjectCreator.py
dbobjectcreator/__init__.py
dbobjectcreator-1.0.15.dist-info/entry_points.txt
dbobjectcreator-1.0.15.dist-info/LICENSE
dbobjectcreator-1.0.15.dist-info/WHEEL
dbobjectcreator-1.0.15.dist-info/METADATA
dbobjectcreator-1.0.15.dist-info/RECORD
